[
  {
    "title": "2012 PSA Party #1",
    "src": "pty027.jpg",
    "tags": "2012",
    "alt": "2012 PSA Party #1",
    "imgDir": "./src/images/party_2012/",
    "outputDir": "/images/party_2012",
    "pathToRoot": "../../..",
    "credit": "Photo by Kevin Trinkle"
  },
  {
    "title": "2012 PSA Party #2",
    "src": "pty019.jpg",
    "tags": "2012",
    "alt": "2012 PSA Party #2",
    "imgDir": "./src/images/party_2012/",
    "outputDir": "/images/party_2012",
    "pathToRoot": "../../..",
    "credit": "Photo by Kevin Trinkle"
  },
  {
    "title": "2012 PSA Party #3",
    "src": "pty028.jpg",
    "tags": "2012",
    "alt": "2012 PSA Party #3",
    "imgDir": "./src/images/party_2012/",
    "outputDir": "/images/party_2012",
    "pathToRoot": "../../..",
    "credit": "Photo by Kevin Trinkle"
  },
  {
    "title": "2012 PSA Party #4",
    "src": "pty038.jpg",
    "tags": "2012",
    "alt": "2012 PSA Party #4",
    "imgDir": "./src/images/party_2012/",
    "outputDir": "/images/party_2012",
    "pathToRoot": "../../..",
    "credit": "Photo by Kevin Trinkle"
  },
  {
    "title": "2012 PSA Party #5",
    "src": "pty036.jpg",
    "tags": "2012",
    "alt": "2012 PSA Party #5",
    "imgDir": "./src/images/party_2012/",
    "outputDir": "/images/party_2012",
    "pathToRoot": "../../..",
    "credit": "Photo by Kevin Trinkle"
  },
  {
    "title": "2012 PSA Party #6",
    "src": "pty016.jpg",
    "tags": "2012",
    "alt": "2012 PSA Party #6",
    "imgDir": "./src/images/party_2012/",
    "outputDir": "/images/party_2012",
    "pathToRoot": "../../..",
    "credit": "Photo by Kevin Trinkle"
  },
  {
    "title": "2012 PSA Party #7",
    "src": "pty015.jpg",
    "tags": "2012",
    "alt": "2012 PSA Party #7",
    "imgDir": "./src/images/party_2012/",
    "outputDir": "/images/party_2012",
    "pathToRoot": "../../..",
    "credit": "Photo by Kevin Trinkle"
  },
  {
    "title": "2012 PSA Party #8",
    "src": "pty009.jpg",
    "tags": "2012",
    "alt": "2012 PSA Party #8",
    "imgDir": "./src/images/party_2012/",
    "outputDir": "/images/party_2012",
    "pathToRoot": "../../..",
    "credit": "Photo by Kevin Trinkle"
  },
  {
    "title": "2012 PSA Party #9",
    "src": "pty026.jpg",
    "tags": "2012",
    "alt": "2012 PSA Party #9",
    "imgDir": "./src/images/party_2012/",
    "outputDir": "/images/party_2012",
    "pathToRoot": "../../..",
    "credit": "Photo by Kevin Trinkle"
  },
  {
    "title": "2012 PSA Party #10",
    "src": "pty018.jpg",
    "tags": "2012",
    "alt": "2012 PSA Party #10",
    "imgDir": "./src/images/party_2012/",
    "outputDir": "/images/party_2012",
    "pathToRoot": "../../..",
    "credit": "Photo by Kevin Trinkle"
  },
  {
    "title": "2012 PSA Party #11",
    "src": "pty039.jpg",
    "tags": "2012",
    "alt": "2012 PSA Party #11",
    "imgDir": "./src/images/party_2012/",
    "outputDir": "/images/party_2012",
    "pathToRoot": "../../..",
    "credit": "Photo by Kevin Trinkle"
  },
  {
    "title": "2012 PSA Party #12",
    "src": "pty029.jpg",
    "tags": "2012",
    "alt": "2012 PSA Party #12",
    "imgDir": "./src/images/party_2012/",
    "outputDir": "/images/party_2012",
    "pathToRoot": "../../..",
    "credit": "Photo by Kevin Trinkle"
  },
  {
    "title": "2012 PSA Party #13",
    "src": "pty005.jpg",
    "tags": "2012",
    "alt": "2012 PSA Party #13",
    "imgDir": "./src/images/party_2012/",
    "outputDir": "/images/party_2012",
    "pathToRoot": "../../..",
    "credit": "Photo by Kevin Trinkle"
  },
  {
    "title": "2012 PSA Party #14",
    "src": "pty004.jpg",
    "tags": "2012",
    "alt": "2012 PSA Party #14",
    "imgDir": "./src/images/party_2012/",
    "outputDir": "/images/party_2012",
    "pathToRoot": "../../..",
    "credit": "Photo by Kevin Trinkle"
  },
  {
    "title": "2012 PSA Party #15",
    "src": "pty037.jpg",
    "tags": "2012",
    "alt": "2012 PSA Party #15",
    "imgDir": "./src/images/party_2012/",
    "outputDir": "/images/party_2012",
    "pathToRoot": "../../..",
    "credit": "Photo by Kevin Trinkle"
  },
  {
    "title": "2012 PSA Party #16",
    "src": "pty006.jpg",
    "tags": "2012",
    "alt": "2012 PSA Party #16",
    "imgDir": "./src/images/party_2012/",
    "outputDir": "/images/party_2012",
    "pathToRoot": "../../..",
    "credit": "Photo by Kevin Trinkle"
  },
  {
    "title": "2012 PSA Party #17",
    "src": "pty007.jpg",
    "tags": "2012",
    "alt": "2012 PSA Party #17",
    "imgDir": "./src/images/party_2012/",
    "outputDir": "/images/party_2012",
    "pathToRoot": "../../..",
    "credit": "Photo by Kevin Trinkle"
  },
  {
    "title": "2012 PSA Party #18",
    "src": "pty003.jpg",
    "tags": "2012",
    "alt": "2012 PSA Party #18",
    "imgDir": "./src/images/party_2012/",
    "outputDir": "/images/party_2012",
    "pathToRoot": "../../..",
    "credit": "Photo by Kevin Trinkle"
  },
  {
    "title": "2012 PSA Party #19",
    "src": "pty023.jpg",
    "tags": "2012",
    "alt": "2012 PSA Party #19",
    "imgDir": "./src/images/party_2012/",
    "outputDir": "/images/party_2012",
    "pathToRoot": "../../..",
    "credit": "Photo by Kevin Trinkle"
  },
  {
    "title": "2012 PSA Party #20",
    "src": "pty017.jpg",
    "tags": "2012",
    "alt": "2012 PSA Party #20",
    "imgDir": "./src/images/party_2012/",
    "outputDir": "/images/party_2012",
    "pathToRoot": "../../..",
    "credit": "Photo by Kevin Trinkle"
  },
  {
    "title": "2012 PSA Party #21",
    "src": "pty002.jpg",
    "tags": "2012",
    "alt": "2012 PSA Party #21",
    "imgDir": "./src/images/party_2012/",
    "outputDir": "/images/party_2012",
    "pathToRoot": "../../..",
    "credit": "Photo by Kevin Trinkle"
  },
  {
    "title": "2012 PSA Party #22",
    "src": "pty001.jpg",
    "tags": "2012",
    "alt": "2012 PSA Party #22",
    "imgDir": "./src/images/party_2012/",
    "outputDir": "/images/party_2012",
    "pathToRoot": "../../..",
    "credit": "Photo by Kevin Trinkle"
  },
  {
    "title": "2012 PSA Party #23",
    "src": "pty010.jpg",
    "tags": "2012",
    "alt": "2012 PSA Party #23",
    "imgDir": "./src/images/party_2012/",
    "outputDir": "/images/party_2012",
    "pathToRoot": "../../..",
    "credit": "Photo by Kevin Trinkle"
  },
  {
    "title": "2012 PSA Party #24",
    "src": "pty030.jpg",
    "tags": "2012",
    "alt": "2012 PSA Party #24",
    "imgDir": "./src/images/party_2012/",
    "outputDir": "/images/party_2012",
    "pathToRoot": "../../..",
    "credit": "Photo by Kevin Trinkle"
  },
  {
    "title": "2012 PSA Party #25",
    "src": "pty031.jpg",
    "tags": "2012",
    "alt": "2012 PSA Party #25",
    "imgDir": "./src/images/party_2012/",
    "outputDir": "/images/party_2012",
    "pathToRoot": "../../..",
    "credit": "Photo by Kevin Trinkle"
  },
  {
    "title": "2012 PSA Party #26",
    "src": "pty032.jpg",
    "tags": "2012",
    "alt": "2012 PSA Party #26",
    "imgDir": "./src/images/party_2012/",
    "outputDir": "/images/party_2012",
    "pathToRoot": "../../..",
    "credit": "Photo by Kevin Trinkle"
  },
  {
    "title": "2012 PSA Party #27",
    "src": "pty033.jpg",
    "tags": "2012",
    "alt": "2012 PSA Party #27",
    "imgDir": "./src/images/party_2012/",
    "outputDir": "/images/party_2012",
    "pathToRoot": "../../..",
    "credit": "Photo by Kevin Trinkle"
  },
  {
    "title": "2012 PSA Party #28",
    "src": "pty034.jpg",
    "tags": "2012",
    "alt": "2012 PSA Party #28",
    "imgDir": "./src/images/party_2012/",
    "outputDir": "/images/party_2012",
    "pathToRoot": "../../..",
    "credit": "Photo by Kevin Trinkle"
  },
  {
    "title": "2012 PSA Party #29",
    "src": "pty035.jpg",
    "tags": "2012",
    "alt": "2012 PSA Party #29",
    "imgDir": "./src/images/party_2012/",
    "outputDir": "/images/party_2012",
    "pathToRoot": "../../..",
    "credit": "Photo by Kevin Trinkle"
  },
  {
    "title": "2012 PSA Party #30",
    "src": "pty008.jpg",
    "tags": "2012",
    "alt": "2012 PSA Party #30",
    "imgDir": "./src/images/party_2012/",
    "outputDir": "/images/party_2012",
    "pathToRoot": "../../..",
    "credit": "Photo by Kevin Trinkle"
  },
  {
    "title": "2012 PSA Party #31",
    "src": "pty011.jpg",
    "tags": "2012",
    "alt": "2012 PSA Party #31",
    "imgDir": "./src/images/party_2012/",
    "outputDir": "/images/party_2012",
    "pathToRoot": "../../..",
    "credit": "Photo by Kevin Trinkle"
  },
  {
    "title": "2012 PSA Party #32",
    "src": "pty012.jpg",
    "tags": "2012",
    "alt": "2012 PSA Party #32",
    "imgDir": "./src/images/party_2012/",
    "outputDir": "/images/party_2012",
    "pathToRoot": "../../..",
    "credit": "Photo by Kevin Trinkle"
  },
  {
    "title": "2012 PSA Party #33",
    "src": "pty013.jpg",
    "tags": "2012",
    "alt": "2012 PSA Party #33",
    "imgDir": "./src/images/party_2012/",
    "outputDir": "/images/party_2012",
    "pathToRoot": "../../..",
    "credit": "Photo by Kevin Trinkle"
  },
  {
    "title": "2012 PSA Party #34",
    "src": "pty014.jpg",
    "tags": "2012",
    "alt": "2012 PSA Party #34",
    "imgDir": "./src/images/party_2012/",
    "outputDir": "/images/party_2012",
    "pathToRoot": "../../..",
    "credit": "Photo by Kevin Trinkle"
  },
  {
    "title": "2012 PSA Party #35",
    "src": "pty040.jpg",
    "tags": "2012",
    "alt": "2012 PSA Party #35",
    "imgDir": "./src/images/party_2012/",
    "outputDir": "/images/party_2012",
    "pathToRoot": "../../..",
    "credit": "Photo by Kevin Trinkle"
  },
  {
    "title": "2012 PSA Party #36",
    "src": "pty041.jpg",
    "tags": "2012",
    "alt": "2012 PSA Party #36",
    "imgDir": "./src/images/party_2012/",
    "outputDir": "/images/party_2012",
    "pathToRoot": "../../..",
    "credit": "Photo by Kevin Trinkle"
  },
  {
    "title": "2012 PSA Party #37",
    "src": "pty042.jpg",
    "tags": "2012",
    "alt": "2012 PSA Party #37",
    "imgDir": "./src/images/party_2012/",
    "outputDir": "/images/party_2012",
    "pathToRoot": "../../..",
    "credit": "Photo by Kevin Trinkle"
  },
  {
    "title": "2012 PSA Party #38",
    "src": "pty043.jpg",
    "tags": "2012",
    "alt": "2012 PSA Party #38",
    "imgDir": "./src/images/party_2012/",
    "outputDir": "/images/party_2012",
    "pathToRoot": "../../..",
    "credit": "Photo by Kevin Trinkle"
  },
  {
    "title": "2012 PSA Party #39",
    "src": "pty045.jpg",
    "tags": "2012",
    "alt": "2012 PSA Party #39",
    "imgDir": "./src/images/party_2012/",
    "outputDir": "/images/party_2012",
    "pathToRoot": "../../..",
    "credit": "Photo by Kevin Trinkle"
  },
  {
    "title": "2012 PSA Party #40",
    "src": "pty046.jpg",
    "tags": "2012",
    "alt": "2012 PSA Party #40",
    "imgDir": "./src/images/party_2012/",
    "outputDir": "/images/party_2012",
    "pathToRoot": "../../..",
    "credit": "Photo by Kevin Trinkle"
  },
  {
    "title": "2012 PSA Party #41",
    "src": "pty047.jpg",
    "tags": "2012",
    "alt": "2012 PSA Party #41",
    "imgDir": "./src/images/party_2012/",
    "outputDir": "/images/party_2012",
    "pathToRoot": "../../..",
    "credit": "Photo by Kevin Trinkle"
  },
  {
    "title": "2012 PSA Party #42",
    "src": "pty048.jpg",
    "tags": "2012",
    "alt": "2012 PSA Party #42",
    "imgDir": "./src/images/party_2012/",
    "outputDir": "/images/party_2012",
    "pathToRoot": "../../..",
    "credit": "Photo by Kevin Trinkle"
  },
  {
    "title": "2012 PSA Party #43",
    "src": "pty049.jpg",
    "tags": "2012",
    "alt": "2012 PSA Party #43",
    "imgDir": "./src/images/party_2012/",
    "outputDir": "/images/party_2012",
    "pathToRoot": "../../..",
    "credit": "Photo by Kevin Trinkle"
  },
  {
    "title": "2012 PSA Party #44",
    "src": "pty050.jpg",
    "tags": "2012",
    "alt": "2012 PSA Party #44",
    "imgDir": "./src/images/party_2012/",
    "outputDir": "/images/party_2012",
    "pathToRoot": "../../..",
    "credit": "Photo by Kevin Trinkle"
  },
  {
    "title": "2012 PSA Party #45",
    "src": "pty051.jpg",
    "tags": "2012",
    "alt": "2012 PSA Party #45",
    "imgDir": "./src/images/party_2012/",
    "outputDir": "/images/party_2012",
    "pathToRoot": "../../..",
    "credit": "Photo by Kevin Trinkle"
  },
  {
    "title": "2012 PSA Party #46",
    "src": "pty052.jpg",
    "tags": "2012",
    "alt": "2012 PSA Party #46",
    "imgDir": "./src/images/party_2012/",
    "outputDir": "/images/party_2012",
    "pathToRoot": "../../..",
    "credit": "Photo by Kevin Trinkle"
  },
  {
    "title": "2012 PSA Party #47",
    "src": "pty053.jpg",
    "tags": "2012",
    "alt": "2012 PSA Party #47",
    "imgDir": "./src/images/party_2012/",
    "outputDir": "/images/party_2012",
    "pathToRoot": "../../..",
    "credit": "Photo by Kevin Trinkle"
  },
  {
    "title": "2012 PSA Party #48",
    "src": "pty054.jpg",
    "tags": "2012",
    "alt": "2012 PSA Party #48",
    "imgDir": "./src/images/party_2012/",
    "outputDir": "/images/party_2012",
    "pathToRoot": "../../..",
    "credit": "Photo by Kevin Trinkle"
  },
  {
    "title": "2012 PSA Party #49",
    "src": "pty055.jpg",
    "tags": "2012",
    "alt": "2012 PSA Party #49",
    "imgDir": "./src/images/party_2012/",
    "outputDir": "/images/party_2012",
    "pathToRoot": "../../..",
    "credit": "Photo by Kevin Trinkle"
  },
  {
    "title": "2012 PSA Party #50",
    "src": "pty056.jpg",
    "tags": "2012",
    "alt": "2012 PSA Party #50",
    "imgDir": "./src/images/party_2012/",
    "outputDir": "/images/party_2012",
    "pathToRoot": "../../..",
    "credit": "Photo by Kevin Trinkle"
  },
  {
    "title": "2012 PSA Party #51",
    "src": "pty057.jpg",
    "tags": "2012",
    "alt": "2012 PSA Party #51",
    "imgDir": "./src/images/party_2012/",
    "outputDir": "/images/party_2012",
    "pathToRoot": "../../..",
    "credit": "Photo by Kevin Trinkle"
  },
  {
    "title": "2012 PSA Party #52",
    "src": "pty058.jpg",
    "tags": "2012",
    "alt": "2012 PSA Party #52",
    "imgDir": "./src/images/party_2012/",
    "outputDir": "/images/party_2012",
    "pathToRoot": "../../..",
    "credit": "Photo by Kevin Trinkle"
  },
  {
    "title": "2012 PSA Party #53",
    "src": "pty061.jpg",
    "tags": "2012",
    "alt": "2012 PSA Party #53",
    "imgDir": "./src/images/party_2012/",
    "outputDir": "/images/party_2012",
    "pathToRoot": "../../..",
    "credit": "Photo by Kevin Trinkle"
  },
  {
    "title": "2012 PSA Party #54",
    "src": "pty062.jpg",
    "tags": "2012",
    "alt": "2012 PSA Party #54",
    "imgDir": "./src/images/party_2012/",
    "outputDir": "/images/party_2012",
    "pathToRoot": "../../..",
    "credit": "Photo by Kevin Trinkle"
  },
  {
    "title": "2012 PSA Party #55",
    "src": "pty063.jpg",
    "tags": "2012",
    "alt": "2012 PSA Party #55",
    "imgDir": "./src/images/party_2012/",
    "outputDir": "/images/party_2012",
    "pathToRoot": "../../..",
    "credit": "Photo by Kevin Trinkle"
  },
  {
    "title": "2012 PSA Party #56",
    "src": "pty064.jpg",
    "tags": "2012",
    "alt": "2012 PSA Party #56",
    "imgDir": "./src/images/party_2012/",
    "outputDir": "/images/party_2012",
    "pathToRoot": "../../..",
    "credit": "Photo by Kevin Trinkle"
  },
  {
    "title": "2012 PSA Party #57",
    "src": "pty066.jpg",
    "tags": "2012",
    "alt": "2012 PSA Party #57",
    "imgDir": "./src/images/party_2012/",
    "outputDir": "/images/party_2012",
    "pathToRoot": "../../..",
    "credit": "Photo by Kevin Trinkle"
  },
  {
    "title": "2012 PSA Party #58",
    "src": "pty067.jpg",
    "tags": "2012",
    "alt": "2012 PSA Party #58",
    "imgDir": "./src/images/party_2012/",
    "outputDir": "/images/party_2012",
    "pathToRoot": "../../..",
    "credit": "Photo by Kevin Trinkle"
  },
  {
    "title": "2012 PSA Party #59",
    "src": "pty068.jpg",
    "tags": "2012",
    "alt": "2012 PSA Party #59",
    "imgDir": "./src/images/party_2012/",
    "outputDir": "/images/party_2012",
    "pathToRoot": "../../..",
    "credit": "Photo by Kevin Trinkle"
  },
  {
    "title": "2012 PSA Party #60",
    "src": "pty069.jpg",
    "tags": "2012",
    "alt": "2012 PSA Party #60",
    "imgDir": "./src/images/party_2012/",
    "outputDir": "/images/party_2012",
    "pathToRoot": "../../..",
    "credit": "Photo by Kevin Trinkle"
  },
  {
    "title": "2012 PSA Party #61",
    "src": "pty070.jpg",
    "tags": "2012",
    "alt": "2012 PSA Party #61",
    "imgDir": "./src/images/party_2012/",
    "outputDir": "/images/party_2012",
    "pathToRoot": "../../..",
    "credit": "Photo by Kevin Trinkle"
  },
  {
    "title": "2012 PSA Party #62",
    "src": "pty071.jpg",
    "tags": "2012",
    "alt": "2012 PSA Party #62",
    "imgDir": "./src/images/party_2012/",
    "outputDir": "/images/party_2012",
    "pathToRoot": "../../..",
    "credit": "Photo by Kevin Trinkle"
  },
  {
    "title": "2012 PSA Party #63",
    "src": "pty073.jpg",
    "tags": "2012",
    "alt": "2012 PSA Party #63",
    "imgDir": "./src/images/party_2012/",
    "outputDir": "/images/party_2012",
    "pathToRoot": "../../..",
    "credit": "Photo by Kevin Trinkle"
  },
  {
    "title": "2012 PSA Party #64",
    "src": "pty074.jpg",
    "tags": "2012",
    "alt": "2012 PSA Party #64",
    "imgDir": "./src/images/party_2012/",
    "outputDir": "/images/party_2012",
    "pathToRoot": "../../..",
    "credit": "Photo by Kevin Trinkle"
  },
  {
    "title": "2012 PSA Party #65",
    "src": "pty075.jpg",
    "tags": "2012",
    "alt": "2012 PSA Party #65",
    "imgDir": "./src/images/party_2012/",
    "outputDir": "/images/party_2012",
    "pathToRoot": "../../..",
    "credit": "Photo by Kevin Trinkle"
  },
  {
    "title": "2012 PSA Party #66",
    "src": "pty076.jpg",
    "tags": "2012",
    "alt": "2012 PSA Party #66",
    "imgDir": "./src/images/party_2012/",
    "outputDir": "/images/party_2012",
    "pathToRoot": "../../..",
    "credit": "Photo by Kevin Trinkle"
  },
  {
    "title": "2012 PSA Party #67",
    "src": "pty077.jpg",
    "tags": "2012",
    "alt": "2012 PSA Party #67",
    "imgDir": "./src/images/party_2012/",
    "outputDir": "/images/party_2012",
    "pathToRoot": "../../..",
    "credit": "Photo by Kevin Trinkle"
  },
  {
    "title": "2012 PSA Party #68",
    "src": "pty078.jpg",
    "tags": "2012",
    "alt": "2012 PSA Party #68",
    "imgDir": "./src/images/party_2012/",
    "outputDir": "/images/party_2012",
    "pathToRoot": "../../..",
    "credit": "Photo by Kevin Trinkle"
  },
  {
    "title": "2012 PSA Party #69",
    "src": "pty079.jpg",
    "tags": "2012",
    "alt": "2012 PSA Party #69",
    "imgDir": "./src/images/party_2012/",
    "outputDir": "/images/party_2012",
    "pathToRoot": "../../..",
    "credit": "Photo by Kevin Trinkle"
  },
  {
    "title": "2012 PSA Party #70",
    "src": "pty080.jpg",
    "tags": "2012",
    "alt": "2012 PSA Party #70",
    "imgDir": "./src/images/party_2012/",
    "outputDir": "/images/party_2012",
    "pathToRoot": "../../..",
    "credit": "Photo by Kevin Trinkle"
  },
  {
    "title": "2012 PSA Party #71",
    "src": "pty081.jpg",
    "tags": "2012",
    "alt": "2012 PSA Party #71",
    "imgDir": "./src/images/party_2012/",
    "outputDir": "/images/party_2012",
    "pathToRoot": "../../..",
    "credit": "Photo by Kevin Trinkle"
  },
  {
    "title": "2012 PSA Party #72",
    "src": "pty082.jpg",
    "tags": "2012",
    "alt": "2012 PSA Party #72",
    "imgDir": "./src/images/party_2012/",
    "outputDir": "/images/party_2012",
    "pathToRoot": "../../..",
    "credit": "Photo by Kevin Trinkle"
  },
  {
    "title": "2012 PSA Party #73",
    "src": "pty084.jpg",
    "tags": "2012",
    "alt": "2012 PSA Party #73",
    "imgDir": "./src/images/party_2012/",
    "outputDir": "/images/party_2012",
    "pathToRoot": "../../..",
    "credit": "Photo by Kevin Trinkle"
  },
  {
    "title": "2012 PSA Party #74",
    "src": "pty085.jpg",
    "tags": "2012",
    "alt": "2012 PSA Party #74",
    "imgDir": "./src/images/party_2012/",
    "outputDir": "/images/party_2012",
    "pathToRoot": "../../..",
    "credit": "Photo by Kevin Trinkle"
  },
  {
    "title": "2012 PSA Party #75",
    "src": "pty086.jpg",
    "tags": "2012",
    "alt": "2012 PSA Party #75",
    "imgDir": "./src/images/party_2012/",
    "outputDir": "/images/party_2012",
    "pathToRoot": "../../..",
    "credit": "Photo by Kevin Trinkle"
  },
  {
    "title": "2012 PSA Party #76",
    "src": "pty087.jpg",
    "tags": "2012",
    "alt": "2012 PSA Party #76",
    "imgDir": "./src/images/party_2012/",
    "outputDir": "/images/party_2012",
    "pathToRoot": "../../..",
    "credit": "Photo by Kevin Trinkle"
  },
  {
    "title": "2012 PSA Party #77",
    "src": "pty088.jpg",
    "tags": "2012",
    "alt": "2012 PSA Party #77",
    "imgDir": "./src/images/party_2012/",
    "outputDir": "/images/party_2012",
    "pathToRoot": "../../..",
    "credit": "Photo by Kevin Trinkle"
  },
  {
    "title": "2012 PSA Party #78",
    "src": "pty089.jpg",
    "tags": "2012",
    "alt": "2012 PSA Party #78",
    "imgDir": "./src/images/party_2012/",
    "outputDir": "/images/party_2012",
    "pathToRoot": "../../..",
    "credit": "Photo by Kevin Trinkle"
  },
  {
    "title": "2012 PSA Party #79",
    "src": "pty090.jpg",
    "tags": "2012",
    "alt": "2012 PSA Party #79",
    "imgDir": "./src/images/party_2012/",
    "outputDir": "/images/party_2012",
    "pathToRoot": "../../..",
    "credit": "Photo by Kevin Trinkle"
  },
  {
    "title": "2012 PSA Party #80",
    "src": "pty091.jpg",
    "tags": "2012",
    "alt": "2012 PSA Party #80",
    "imgDir": "./src/images/party_2012/",
    "outputDir": "/images/party_2012",
    "pathToRoot": "../../..",
    "credit": "Photo by Kevin Trinkle"
  },
  {
    "title": "2012 PSA Party #81",
    "src": "pty092.jpg",
    "tags": "2012",
    "alt": "2012 PSA Party #81",
    "imgDir": "./src/images/party_2012/",
    "outputDir": "/images/party_2012",
    "pathToRoot": "../../..",
    "credit": "Photo by Kevin Trinkle"
  },
  {
    "title": "2012 PSA Party #82",
    "src": "pty093.jpg",
    "tags": "2012",
    "alt": "2012 PSA Party #82",
    "imgDir": "./src/images/party_2012/",
    "outputDir": "/images/party_2012",
    "pathToRoot": "../../..",
    "credit": "Photo by Kevin Trinkle"
  },
  {
    "title": "2012 PSA Party #83",
    "src": "pty094.jpg",
    "tags": "2012",
    "alt": "2012 PSA Party #83",
    "imgDir": "./src/images/party_2012/",
    "outputDir": "/images/party_2012",
    "pathToRoot": "../../..",
    "credit": "Photo by Kevin Trinkle"
  },
  {
    "title": "2012 PSA Party #84",
    "src": "pty095.jpg",
    "tags": "2012",
    "alt": "2012 PSA Party #84",
    "imgDir": "./src/images/party_2012/",
    "outputDir": "/images/party_2012",
    "pathToRoot": "../../..",
    "credit": "Photo by Kevin Trinkle"
  },
  {
    "title": "2012 PSA Party #85",
    "src": "pty097.jpg",
    "tags": "2012",
    "alt": "2012 PSA Party #85",
    "imgDir": "./src/images/party_2012/",
    "outputDir": "/images/party_2012",
    "pathToRoot": "../../..",
    "credit": "Photo by Kevin Trinkle"
  },
  {
    "title": "2012 PSA Party #86",
    "src": "pty100.jpg",
    "tags": "2012",
    "alt": "2012 PSA Party #86",
    "imgDir": "./src/images/party_2012/",
    "outputDir": "/images/party_2012",
    "pathToRoot": "../../..",
    "credit": "Photo by Kevin Trinkle"
  },
  {
    "title": "2012 PSA Party #87",
    "src": "pty101.jpg",
    "tags": "2012",
    "alt": "2012 PSA Party #87",
    "imgDir": "./src/images/party_2012/",
    "outputDir": "/images/party_2012",
    "pathToRoot": "../../..",
    "credit": "Photo by Kevin Trinkle"
  },
  {
    "title": "2012 PSA Party #88",
    "src": "pty103.jpg",
    "tags": "2012",
    "alt": "2012 PSA Party #88",
    "imgDir": "./src/images/party_2012/",
    "outputDir": "/images/party_2012",
    "pathToRoot": "../../..",
    "credit": "Photo by Kevin Trinkle"
  },
  {
    "title": "2012 PSA Party #89",
    "src": "pty104.jpg",
    "tags": "2012",
    "alt": "2012 PSA Party #89",
    "imgDir": "./src/images/party_2012/",
    "outputDir": "/images/party_2012",
    "pathToRoot": "../../..",
    "credit": "Photo by Kevin Trinkle"
  },
  {
    "title": "2012 PSA Party #90",
    "src": "pty107.jpg",
    "tags": "2012",
    "alt": "2012 PSA Party #90",
    "imgDir": "./src/images/party_2012/",
    "outputDir": "/images/party_2012",
    "pathToRoot": "../../..",
    "credit": "Photo by Kevin Trinkle"
  },
  {
    "title": "2012 PSA Party #91",
    "src": "pty108.jpg",
    "tags": "2012",
    "alt": "2012 PSA Party #91",
    "imgDir": "./src/images/party_2012/",
    "outputDir": "/images/party_2012",
    "pathToRoot": "../../..",
    "credit": "Photo by Kevin Trinkle"
  },
  {
    "title": "2012 PSA Party #92",
    "src": "pty109.jpg",
    "tags": "2012",
    "alt": "2012 PSA Party #92",
    "imgDir": "./src/images/party_2012/",
    "outputDir": "/images/party_2012",
    "pathToRoot": "../../..",
    "credit": "Photo by Kevin Trinkle"
  },
  {
    "title": "2012 PSA Party #93",
    "src": "pty110.jpg",
    "tags": "2012",
    "alt": "2012 PSA Party #93",
    "imgDir": "./src/images/party_2012/",
    "outputDir": "/images/party_2012",
    "pathToRoot": "../../..",
    "credit": "Photo by Kevin Trinkle"
  },
  {
    "title": "2012 PSA Party #94",
    "src": "pty111.jpg",
    "tags": "2012",
    "alt": "2012 PSA Party #94",
    "imgDir": "./src/images/party_2012/",
    "outputDir": "/images/party_2012",
    "pathToRoot": "../../..",
    "credit": "Photo by Kevin Trinkle"
  },
  {
    "title": "2012 PSA Party #95",
    "src": "pty113.jpg",
    "tags": "2012",
    "alt": "2012 PSA Party #95",
    "imgDir": "./src/images/party_2012/",
    "outputDir": "/images/party_2012",
    "pathToRoot": "../../..",
    "credit": "Photo by Kevin Trinkle"
  },
  {
    "title": "2012 PSA Party #96",
    "src": "pty114.jpg",
    "tags": "2012",
    "alt": "2012 PSA Party #96",
    "imgDir": "./src/images/party_2012/",
    "outputDir": "/images/party_2012",
    "pathToRoot": "../../..",
    "credit": "Photo by Kevin Trinkle"
  },
  {
    "title": "2012 PSA Party #97",
    "src": "pty115.jpg",
    "tags": "2012",
    "alt": "2012 PSA Party #97",
    "imgDir": "./src/images/party_2012/",
    "outputDir": "/images/party_2012",
    "pathToRoot": "../../..",
    "credit": "Photo by Kevin Trinkle"
  },
  {
    "title": "2012 PSA Party #98",
    "src": "pty116.jpg",
    "tags": "2012",
    "alt": "2012 PSA Party #98",
    "imgDir": "./src/images/party_2012/",
    "outputDir": "/images/party_2012",
    "pathToRoot": "../../..",
    "credit": "Photo by Kevin Trinkle"
  },
  {
    "title": "2012 PSA Party #99",
    "src": "pty117.jpg",
    "tags": "2012",
    "alt": "2012 PSA Party #99",
    "imgDir": "./src/images/party_2012/",
    "outputDir": "/images/party_2012",
    "pathToRoot": "../../..",
    "credit": "Photo by Kevin Trinkle"
  },
  {
    "title": "2012 PSA Party #100",
    "src": "pty118.jpg",
    "tags": "2012",
    "alt": "2012 PSA Party #100",
    "imgDir": "./src/images/party_2012/",
    "outputDir": "/images/party_2012",
    "pathToRoot": "../../..",
    "credit": "Photo by Kevin Trinkle"
  },
  {
    "title": "2012 PSA Party #101",
    "src": "pty119.jpg",
    "tags": "2012",
    "alt": "2012 PSA Party #101",
    "imgDir": "./src/images/party_2012/",
    "outputDir": "/images/party_2012",
    "pathToRoot": "../../..",
    "credit": "Photo by Kevin Trinkle"
  },
  {
    "title": "2012 PSA Party #102",
    "src": "pty120.jpg",
    "tags": "2012",
    "alt": "2012 PSA Party #102",
    "imgDir": "./src/images/party_2012/",
    "outputDir": "/images/party_2012",
    "pathToRoot": "../../..",
    "credit": "Photo by Kevin Trinkle"
  },
  {
    "title": "2012 PSA Party #103",
    "src": "pty121.jpg",
    "tags": "2012",
    "alt": "2012 PSA Party #103",
    "imgDir": "./src/images/party_2012/",
    "outputDir": "/images/party_2012",
    "pathToRoot": "../../..",
    "credit": "Photo by Kevin Trinkle"
  },
  {
    "title": "2012 PSA Party #104",
    "src": "pty122.jpg",
    "tags": "2012",
    "alt": "2012 PSA Party #104",
    "imgDir": "./src/images/party_2012/",
    "outputDir": "/images/party_2012",
    "pathToRoot": "../../..",
    "credit": "Photo by Kevin Trinkle"
  },
  {
    "title": "2012 PSA Party #105",
    "src": "pty123.jpg",
    "tags": "2012",
    "alt": "2012 PSA Party #105",
    "imgDir": "./src/images/party_2012/",
    "outputDir": "/images/party_2012",
    "pathToRoot": "../../..",
    "credit": "Photo by Kevin Trinkle"
  },
  {
    "title": "2012 PSA Party #106",
    "src": "pty127.jpg",
    "tags": "2012",
    "alt": "2012 PSA Party #106",
    "imgDir": "./src/images/party_2012/",
    "outputDir": "/images/party_2012",
    "pathToRoot": "../../..",
    "credit": "Photo by Kevin Trinkle"
  },
  {
    "title": "2012 PSA Party #107",
    "src": "pty128.jpg",
    "tags": "2012",
    "alt": "2012 PSA Party #107",
    "imgDir": "./src/images/party_2012/",
    "outputDir": "/images/party_2012",
    "pathToRoot": "../../..",
    "credit": "Photo by Kevin Trinkle"
  },
  {
    "title": "2012 PSA Party #108",
    "src": "pty129.jpg",
    "tags": "2012",
    "alt": "2012 PSA Party #108",
    "imgDir": "./src/images/party_2012/",
    "outputDir": "/images/party_2012",
    "pathToRoot": "../../..",
    "credit": "Photo by Kevin Trinkle"
  },
  {
    "title": "2012 PSA Party #109",
    "src": "pty130.jpg",
    "tags": "2012",
    "alt": "2012 PSA Party #109",
    "imgDir": "./src/images/party_2012/",
    "outputDir": "/images/party_2012",
    "pathToRoot": "../../..",
    "credit": "Photo by Kevin Trinkle"
  },
  {
    "title": "2012 PSA Party #110",
    "src": "pty131.jpg",
    "tags": "2012",
    "alt": "2012 PSA Party #110",
    "imgDir": "./src/images/party_2012/",
    "outputDir": "/images/party_2012",
    "pathToRoot": "../../..",
    "credit": "Photo by Kevin Trinkle"
  },
  {
    "title": "2012 PSA Party #111",
    "src": "pty132.jpg",
    "tags": "2012",
    "alt": "2012 PSA Party #111",
    "imgDir": "./src/images/party_2012/",
    "outputDir": "/images/party_2012",
    "pathToRoot": "../../..",
    "credit": "Photo by Kevin Trinkle"
  },
  {
    "title": "2012 PSA Party #112",
    "src": "pty133.jpg",
    "tags": "2012",
    "alt": "2012 PSA Party #112",
    "imgDir": "./src/images/party_2012/",
    "outputDir": "/images/party_2012",
    "pathToRoot": "../../..",
    "credit": "Photo by Kevin Trinkle"
  },
  {
    "title": "2012 PSA Party #113",
    "src": "pty134.jpg",
    "tags": "2012",
    "alt": "2012 PSA Party #113",
    "imgDir": "./src/images/party_2012/",
    "outputDir": "/images/party_2012",
    "pathToRoot": "../../..",
    "credit": "Photo by Kevin Trinkle"
  },
  {
    "title": "2012 PSA Party #114",
    "src": "pty135.jpg",
    "tags": "2012",
    "alt": "2012 PSA Party #114",
    "imgDir": "./src/images/party_2012/",
    "outputDir": "/images/party_2012",
    "pathToRoot": "../../..",
    "credit": "Photo by Kevin Trinkle"
  },
  {
    "title": "2012 PSA Party #115",
    "src": "pty136.jpg",
    "tags": "2012",
    "alt": "2012 PSA Party #115",
    "imgDir": "./src/images/party_2012/",
    "outputDir": "/images/party_2012",
    "pathToRoot": "../../..",
    "credit": "Photo by Kevin Trinkle"
  },
  {
    "title": "2012 PSA Party #116",
    "src": "pty137.jpg",
    "tags": "2012",
    "alt": "2012 PSA Party #116",
    "imgDir": "./src/images/party_2012/",
    "outputDir": "/images/party_2012",
    "pathToRoot": "../../..",
    "credit": "Photo by Kevin Trinkle"
  },
  {
    "title": "2012 PSA Party #117",
    "src": "pty138.jpg",
    "tags": "2012",
    "alt": "2012 PSA Party #117",
    "imgDir": "./src/images/party_2012/",
    "outputDir": "/images/party_2012",
    "pathToRoot": "../../..",
    "credit": "Photo by Kevin Trinkle"
  },
  {
    "title": "2012 PSA Party #118",
    "src": "pty139.jpg",
    "tags": "2012",
    "alt": "2012 PSA Party #118",
    "imgDir": "./src/images/party_2012/",
    "outputDir": "/images/party_2012",
    "pathToRoot": "../../..",
    "credit": "Photo by Kevin Trinkle"
  },
  {
    "title": "2012 PSA Party #119",
    "src": "pty142.jpg",
    "tags": "2012",
    "alt": "2012 PSA Party #119",
    "imgDir": "./src/images/party_2012/",
    "outputDir": "/images/party_2012",
    "pathToRoot": "../../..",
    "credit": "Photo by Kevin Trinkle"
  },
  {
    "title": "2012 PSA Party #120",
    "src": "pty143.jpg",
    "tags": "2012",
    "alt": "2012 PSA Party #120",
    "imgDir": "./src/images/party_2012/",
    "outputDir": "/images/party_2012",
    "pathToRoot": "../../..",
    "credit": "Photo by Kevin Trinkle"
  },
  {
    "title": "2012 PSA Party #121",
    "src": "pty145.jpg",
    "tags": "2012",
    "alt": "2012 PSA Party #121",
    "imgDir": "./src/images/party_2012/",
    "outputDir": "/images/party_2012",
    "pathToRoot": "../../..",
    "credit": "Photo by Kevin Trinkle"
  },
  {
    "title": "2012 PSA Party #122",
    "src": "pty147.jpg",
    "tags": "2012",
    "alt": "2012 PSA Party #122",
    "imgDir": "./src/images/party_2012/",
    "outputDir": "/images/party_2012",
    "pathToRoot": "../../..",
    "credit": "Photo by Kevin Trinkle"
  },
  {
    "title": "2012 PSA Party #123",
    "src": "pty151.jpg",
    "tags": "2012",
    "alt": "2012 PSA Party #123",
    "imgDir": "./src/images/party_2012/",
    "outputDir": "/images/party_2012",
    "pathToRoot": "../../..",
    "credit": "Photo by Kevin Trinkle"
  },
  {
    "title": "2012 PSA Party #124",
    "src": "pty152.jpg",
    "tags": "2012",
    "alt": "2012 PSA Party #124",
    "imgDir": "./src/images/party_2012/",
    "outputDir": "/images/party_2012",
    "pathToRoot": "../../..",
    "credit": "Photo by Kevin Trinkle"
  },
  {
    "title": "2012 PSA Party #125",
    "src": "pty154.jpg",
    "tags": "2012",
    "alt": "2012 PSA Party #125",
    "imgDir": "./src/images/party_2012/",
    "outputDir": "/images/party_2012",
    "pathToRoot": "../../..",
    "credit": "Photo by Kevin Trinkle"
  },
  {
    "title": "2012 PSA Party #126",
    "src": "pty155.jpg",
    "tags": "2012",
    "alt": "2012 PSA Party #126",
    "imgDir": "./src/images/party_2012/",
    "outputDir": "/images/party_2012",
    "pathToRoot": "../../..",
    "credit": "Photo by Kevin Trinkle"
  },
  {
    "title": "2012 PSA Party #127",
    "src": "pty156.jpg",
    "tags": "2012",
    "alt": "2012 PSA Party #127",
    "imgDir": "./src/images/party_2012/",
    "outputDir": "/images/party_2012",
    "pathToRoot": "../../..",
    "credit": "Photo by Kevin Trinkle"
  },
  {
    "title": "2012 PSA Party #128",
    "src": "pty157.jpg",
    "tags": "2012",
    "alt": "2012 PSA Party #128",
    "imgDir": "./src/images/party_2012/",
    "outputDir": "/images/party_2012",
    "pathToRoot": "../../..",
    "credit": "Photo by Kevin Trinkle"
  },
  {
    "title": "2012 PSA Party #129",
    "src": "pty159.jpg",
    "tags": "2012",
    "alt": "2012 PSA Party #129",
    "imgDir": "./src/images/party_2012/",
    "outputDir": "/images/party_2012",
    "pathToRoot": "../../..",
    "credit": "Photo by Kevin Trinkle"
  },
  {
    "title": "2012 PSA Party #130",
    "src": "pty161.jpg",
    "tags": "2012",
    "alt": "2012 PSA Party #130",
    "imgDir": "./src/images/party_2012/",
    "outputDir": "/images/party_2012",
    "pathToRoot": "../../..",
    "credit": "Photo by Kevin Trinkle"
  },
  {
    "title": "2012 PSA Party #131",
    "src": "pty163.jpg",
    "tags": "2012",
    "alt": "2012 PSA Party #131",
    "imgDir": "./src/images/party_2012/",
    "outputDir": "/images/party_2012",
    "pathToRoot": "../../..",
    "credit": "Photo by Kevin Trinkle"
  },
  {
    "title": "2012 PSA Party #132",
    "src": "pty164.jpg",
    "tags": "2012",
    "alt": "2012 PSA Party #132",
    "imgDir": "./src/images/party_2012/",
    "outputDir": "/images/party_2012",
    "pathToRoot": "../../..",
    "credit": "Photo by Kevin Trinkle"
  },
  {
    "title": "2012 PSA Party #133",
    "src": "pty167.jpg",
    "tags": "2012",
    "alt": "2012 PSA Party #133",
    "imgDir": "./src/images/party_2012/",
    "outputDir": "/images/party_2012",
    "pathToRoot": "../../..",
    "credit": "Photo by Kevin Trinkle"
  }
]
